ctfdfetch/__init__.py
ctfdfetch/ctfd.py
ctfdfetch/ctfdfetch.py
ctfdfetch/store.py
ctfdfetch/utils.py
ctfdfetch/templates/challenges.md.j2
ctfdfetch/templates/description.md.j2
ctfdfetch-0.2.0.dist-info/METADATA
ctfdfetch-0.2.0.dist-info/RECORD
ctfdfetch-0.2.0.dist-info/WHEEL
ctfdfetch-0.2.0.dist-info/entry_points.txt
ctfdfetch-0.2.0.dist-info/top_level.txt
