Metadata-Version: 2.1
Name: ctfdfetch
Version: 0.2.0
Summary: Fetch challenges from a CTFd competition
Home-page: https://gitlab.com/royragsdale/ctfdfetch
Author: Roy Ragsdale
License: UNKNOWN
Project-URL: Source, https://gitlab.com/royragsdale/ctfdfetch
Project-URL: Bug Reports, https://gitlab.com/royragsdale/ctfdfetch/issues
Keywords: ctf
Platform: UNKNOWN
Classifier: Development Status :: 3 - Alpha
Classifier: License :: OSI Approved :: MIT License
Classifier: Programming Language :: Python :: 3
Classifier: Programming Language :: Python :: 3.4
Classifier: Programming Language :: Python :: 3.5
Classifier: Programming Language :: Python :: 3.6
Requires-Python: >=3
Requires-Dist: beautifulsoup4
Requires-Dist: jinja2
Requires-Dist: Markdown
Requires-Dist: requests
Requires-Dist: tld
